[
    {
        "id": "mining-pig",
        "name": "挖矿猪",
        "description": "水晶还不够",
        "analysis": "你举着钻石镐疯狂刨水晶，活动剧情读完了、地图小人点遍了、歌曲FC也刷满了——一切都是为了攒够下次卡池的保底。你是猪圈里最勤劳的零氪矿工，钱包虽然空的，但对推的执念比矿石还硬。"
    },
    {
        "id": "ranking-pig",
        "name": "猪冲榜",
        "description": "还差亿点",
        "analysis": "你双眼翻白、周围堆满了火罐，水晶见底了但排名还差一大截。活动剧情读了三遍、协力打到手抽筋、每一罐体力都不敢浪费——你是猪圈里最拼命的冲榜选手，赌上一切只为推的那个限定称号。"
    },
    {
        "id": "attendance-pig",
        "name": "猪出勤",
        "description": "堵门中",
        "analysis": "你戴好手套、塞上耳机、书包里塞满大水，一副标准的机厅出勤装备。你是猪圈里最忠实的音游选手——日均出勤四小时起步，AP数比吃过的饲料还多。别的猪问你为什么天天去，你只说了两个字：「出勤。」"
    }
]
